{
  "boxes": [
    {
      "label": "blue_cone",
      "x": 271.5,
      "y": 335.0,
      "width": 13,
      "height": 16,
      "keypoints": null
    },
    {
      "label": "blue_cone",
      "x": 11.5,
      "y": 371.5,
      "width": 21,
      "height": 23,
      "keypoints": null
    },
    {
      "label": "blue_cone",
      "x": 635.0,
      "y": 338.5,
      "width": 10,
      "height": 17,
      "keypoints": null
    },
    {
      "label": "orange_cone",
      "x": 332.5,
      "y": 320.0,
      "width": 9,
      "height": 14,
      "keypoints": null
    },
    {
      "label": "orange_cone",
      "x": 114.5,
      "y": 314.0,
      "width": 9,
      "height": 12,
      "keypoints": null
    },
    {
      "label": "orange_cone",
      "x": 485.0,
      "y": 323.0,
      "width": 10,
      "height": 14,
      "keypoints": null
    },
    {
      "label": "yellow_cone",
      "x": 290.0,
      "y": 495.5,
      "width": 40,
      "height": 47,
      "keypoints": null
    },
    {
      "label": "yellow_cone",
      "x": 312.5,
      "y": 355.0,
      "width": 17,
      "height": 20,
      "keypoints": null
    }
  ],
  "height": 640,
  "key": "images/000504.jpg",
  "width": 640
}